{
   "$id":"api_v1_login_endpoint",
   "$schema":"http://json-schema.org/draft-07/schema#",
   "title":"login_endpoint",
   "type":"object",
   "properties":{
      "email":{
         "id":"email",
         "type":"string",
         "format":"email",
         "description":"The email",
         "minLength":3,
         "maxLength":20
      },
      "password":{
         "id":"password",
         "type":"string",
         "description":"The password",
         "minLength":6,
         "maxLength":20
      }
   },
   "required":[
      "email",
      "password"
   ]
}
